extractorx/__init__.py
extractorx/api.py
extractorx-0.0.1.dist-info/LICENSE
extractorx-0.0.1.dist-info/METADATA
extractorx-0.0.1.dist-info/WHEEL
extractorx-0.0.1.dist-info/top_level.txt
extractorx-0.0.1.dist-info/RECORD
