Metadata-Version: 2.1
Name: extractorx
Version: 0.0.1
Summary: ExtractorX Python API Wrapper
Home-page: https://github.com/trevormcguire/extractorx
Author: Trevor McGuire
Author-email: trevormcguire13@gmail.com
Maintainer: Trevor McGuire
License: BSD 3-Clause License
Classifier: Programming Language :: Python :: 3
Classifier: Programming Language :: Python :: Implementation :: CPython
Classifier: Development Status :: 3 - Alpha
License-File: LICENSE
Requires-Dist: requests
